README.txt
setup.py
twill-fork
retwill.egg-info/PKG-INFO
retwill.egg-info/SOURCES.txt
retwill.egg-info/dependency_links.txt
retwill.egg-info/entry_points.txt
retwill.egg-info/requires.txt
retwill.egg-info/top_level.txt
twill/__init__.py
twill/browser.py
twill/commands.py
twill/config.py
twill/errors.py
twill/logconfig.py
twill/namespaces.py
twill/parse.py
twill/shell.py
twill/unit.py
twill/utils.py
twill/extensions/__init__.py
twill/extensions/argparse.py
twill/extensions/check_links.py
twill/extensions/csv_iterate.py
twill/extensions/dirstack.py
twill/extensions/dns_check.py
twill/extensions/formfill.py
twill/extensions/mailman_sf.py
twill/extensions/require.py
twill/extensions/test_extensions.py
twill/extensions/match_parse/__init__.py
twill/extensions/match_parse/test-match_parse.py