Metadata-Version: 1.1
Name: retwill
Version: 1.0.0
Summary: retwill - fork of C. Titus Brown's twill Web browsing language
Home-page: http://bitbucket.org/brandizzi/retwill/
Author: Adam Victor Nazareth Brandizzi 
Author-email: brandizzi@gmail.com
License: UNKNOWN
Download-URL: https://bitbucket.org/brandizzi/retwill/downloads/retwill-1.0.0.tar.gz
Platform: UNKNOWN
Classifier: Development Status :: 4 - Beta
Classifier: Environment :: Console
Classifier: Intended Audience :: Developers
Classifier: Intended Audience :: System Administrators
Classifier: License :: OSI Approved :: MIT License
Classifier: Natural Language :: English
Classifier: Operating System :: OS Independent
Classifier: Programming Language :: Python
Classifier: Programming Language :: Other Scripting Engines
Classifier: Topic :: Internet :: WWW/HTTP
Classifier: Topic :: Software Development :: Testing
Obsoletes: t
Obsoletes: w
Obsoletes: i
Obsoletes: l
Obsoletes: l
